examples/__init__.py
examples/binary_classification.py
examples/multi_classification.py
examples/regression.py
starboost/__init__.py
starboost/__version__.py
starboost/boosting.py
starboost/init.py
starboost/line_searchers.py
starboost/loss.py
starboost/losses.py
starboost/tests/__init__.py
starboost/tests/test_classification.py
starboost/tests/test_regression.py
starboost-0.0.2.dist-info/METADATA
starboost-0.0.2.dist-info/RECORD
starboost-0.0.2.dist-info/WHEEL
starboost-0.0.2.dist-info/top_level.txt
