Metadata-Version: 2.1
Name: starboost
Version: 0.0.2
Summary: A small machine learning library for doing gradient boosting
Home-page: https://github.com/MaxHalford/starboost
Author: Max Halford
Author-email: maxhalford25@gmail.com
License: MIT
Platform: UNKNOWN
Classifier: License :: OSI Approved :: MIT License
Classifier: Programming Language :: Python
Classifier: Programming Language :: Python :: 3
Classifier: Programming Language :: Python :: 3.5
Classifier: Programming Language :: Python :: 3.6
Classifier: Programming Language :: Python :: Implementation :: CPython
Classifier: Programming Language :: Python :: Implementation :: PyPy
Requires-Python: >=3.5.0
Requires-Dist: numpy (>=1.14.0)
Requires-Dist: scipy (>=1.0.1)
Requires-Dist: scikit-learn (>=0.19.0)
